{
  "task": "can",
  "mechanism": "gated",
  "seq_len": 32,
  "test_seq_len": 32,
  "input_dim": 93,
  "num_classes": 2,
  "latch_kind": null,
  "hard_state": null,
  "hard_control": null,
  "anneal": null,
  "hidden": 128,
  "cell_layers": 2,
  "keep_bias": 1.0,
  "tau": 30.0,
  "grad_factor": 1.0,
  "grad_clip": 1.0,
  "lr": 0.01,
  "lr_min": -1.0,
  "entropy_reg": 0.0,
  "entropy_ramp": 1.0,
  "margin_reg": 0.0,
  "deep_sup": 0.2,
  "running_target": false,
  "alphabet": 8,
  "chunk": 1,
  "delay": 0,
  "distractors": 8,
  "sel_flag": false,
  "init_from": "",
  "eval_freq": 75,
  "tag": "c0g_reverify_speedo_cpu",
  "state_mushy_by_t": null,
  "batch_size": 128,
  "iters": 150,
  "seed": 0,
  "device": "cpu",
  "logic_gates": 512,
  "best_val": 0.9695340501792115,
  "test_acc": 0.9790252930289944,
  "test_soft": 0.9790252930289944,
  "discretization_gap": 0.0,
  "n_skipped": 0,
  "train_minutes": 4.184050452709198,
  "can_source": "road",
  "can_file": null,
  "can_attack": "max_speedometer+masquerade",
  "can_ambient": false,
  "can_window": 32,
  "can_stride": 8,
  "can_eval_stride": 128,
  "can_id_enc": "onehot",
  "can_top_ids": 20,
  "can_dt_bins": 8,
  "can_dt_global": false,
  "can_dt_edges": [
    0.0010240077972412112,
    0.002737392377387569,
    0.007317636689844923,
    0.019561611688152642,
    0.052292381824462913,
    0.13978874749525613,
    0.3736852911364432,
    0.998940896987915
  ],
  "can_dt_edges_global": null,
  "can_id_vocab": [
    "0x00E",
    "0x033",
    "0x0A7",
    "0x0C0",
    "0x0D0",
    "0x107",
    "0x125",
    "0x153",
    "0x162",
    "0x193",
    "0x19C",
    "0x20E",
    "0x230",
    "0x274",
    "0x28B",
    "0x354",
    "0x5E1",
    "0x69E",
    "0x6E0",
    "0xFFF"
  ],
  "can_payload_bytes": 8,
  "can_per_step": true,
  "can_flatten": false,
  "can_split": {
    "max_speedometer_attack_1_masquerade": "train",
    "max_speedometer_attack_2_masquerade": "val",
    "max_speedometer_attack_3_masquerade": "test"
  },
  "can_split_boundaries": {
    "max_speedometer_attack_1_masquerade": [
      [
        "train",
        1140000000.0,
        1140000088.021577
      ]
    ],
    "max_speedometer_attack_2_masquerade": [
      [
        "val",
        1150000000.0,
        1150000059.696973
      ]
    ],
    "max_speedometer_attack_3_masquerade": [
      [
        "test",
        1160000000.0,
        1160000086.766667
      ]
    ]
  },
  "can_frames": {
    "train": 210953,
    "val": 142754,
    "test": 207444
  },
  "can_windows": {
    "train": 26366,
    "val": 1116,
    "test": 1621
  },
  "can_attack_frac": {
    "train": 0.011580778656857214,
    "val": 0.02198887596844922,
    "test": 0.029439270357301248
  },
  "can_attack_frac_windows_test": 0.02097470685839653,
  "test_tp": 0,
  "test_fp": 0,
  "test_tn": 1587,
  "test_fn": 34,
  "test_fpr": 0.0,
  "test_recall": 0.0,
  "test_precision": null,
  "test_f1": 0.0,
  "grad_profile": null,
  "gate_totals": [
    42,
    46,
    29,
    27,
    33,
    29,
    17,
    31,
    22,
    16,
    27,
    38,
    28,
    36,
    35,
    56
  ],
  "gate_distribution": {
    "cell.candidate.net.0": [
      9,
      13,
      5,
      9,
      10,
      6,
      5,
      12,
      1,
      3,
      8,
      8,
      5,
      13,
      12,
      9
    ],
    "cell.candidate.net.1": [
      12,
      11,
      8,
      10,
      6,
      8,
      5,
      8,
      8,
      4,
      3,
      9,
      11,
      6,
      9,
      10
    ],
    "cell.gate.net.0": [
      11,
      15,
      6,
      2,
      10,
      7,
      5,
      8,
      6,
      6,
      6,
      14,
      5,
      10,
      10,
      7
    ],
    "cell.gate.net.1": [
      10,
      7,
      10,
      6,
      7,
      8,
      2,
      3,
      7,
      3,
      10,
      7,
      7,
      7,
      4,
      30
    ]
  }
}